func_parallelizer/__init__.py
func_parallelizer/func_parallelizer.py
func_parallelizer-0.4.1.dist-info/METADATA
func_parallelizer-0.4.1.dist-info/WHEEL
func_parallelizer-0.4.1.dist-info/top_level.txt
func_parallelizer-0.4.1.dist-info/RECORD
