Metadata-Version: 2.1
Name: func_parallelizer
Version: 0.4.1
Summary: Func_Parallelizer is a simple Python module for parallel execution of functions using multiprocessing. Ideal for parallel execution of heavy cpu operations
Author: Vikash G
Author-email: vikashgraja@gmail.com
Project-URL: PyPi Funding, https://donate.pypi.org
Project-URL: Code, https://github.com/vikashgraja/Func_Parallelizer
Project-URL: Pull requests, https://github.com/vikashgraja/Func_Parallelizer/pulls
Project-URL: Issues, https://github.com/vikashgraja/Func_Parallelizer/issues
Keywords: multiprocessing
Classifier: Programming Language :: Python :: 3
Classifier: License :: OSI Approved :: MIT License
Classifier: Operating System :: OS Independent
Requires-Python: >=3.6
